{"v":"5.3.4","fr":25,"ip":0,"op":119,"w":265,"h":140,"nm":"EcranTutorielFinal","ddd":0,"assets":[{"id":"comp_0","layers":[{"ddd":0,"ind":1,"ty":5,"nm":"action B","sr":1,"ks":{"o":{"a":1,"k":[{"i":{"x":[0.833],"y":[0.833]},"o":{"x":[0.167],"y":[0.167]},"n":["0p833_0p833_0p167_0p167"],"t":47,"s":[0],"e":[100]},{"i":{"x":[0.833],"y":[0.833]},"o":{"x":[0.167],"y":[0.167]},"n":["0p833_0p833_0p167_0p167"],"t":57,"s":[100],"e":[100]},{"i":{"x":[0.833],"y":[0.833]},"o":{"x":[0.167],"y":[0.167]},"n":["0p833_0p833_0p167_0p167"],"t":82,"s":[100],"e":[0]},{"t":86}],"ix":11},"r":{"a":0,"k":0,"ix":10},"p":{"a":0,"k":[302.5,88.25,0],"ix":2},"a":{"a":0,"k":[0,0,0],"ix":1},"s":{"a":0,"k":[100,100,100],"ix":6}},"ao":0,"t":{"d":{"k":[{"s":{"sz":[149.5,38.5],"ps":[-70,-19.25],"s":20,"f":"FivoSansModern-Heavy","t":"action B","j":2,"tr":0,"lh":24,"ls":0,"fc":[1,1,1]},"t":0}]},"p":{},"m":{"g":1,"a":{"a":0,"k":[0,0],"ix":2}},"a":[]},"ip":0,"op":375,"st":0,"bm":0},{"ddd":0,"ind":2,"ty":5,"nm":"action A","sr":1,"ks":{"o":{"a":1,"k":[{"i":{"x":[0.833],"y":[0.833]},"o":{"x":[0.167],"y":[0.167]},"n":["0p833_0p833_0p167_0p167"],"t":17,"s":[0],"e":[100]},{"i":{"x":[0.833],"y":[0.833]},"o":{"x":[0.167],"y":[0.167]},"n":["0p833_0p833_0p167_0p167"],"t":27,"s":[100],"e":[100]},{"i":{"x":[0.833],"y":[0.833]},"o":{"x":[0.167],"y":[0.167]},"n":["0p833_0p833_0p167_0p167"],"t":40,"s":[100],"e":[0]},{"i":{"x":[0.833],"y":[0.833]},"o":{"x":[0.167],"y":[0.167]},"n":["0p833_0p833_0p167_0p167"],"t":47,"s":[0],"e":[0]},{"i":{"x":[0.833],"y":[0.833]},"o":{"x":[0.167],"y":[0.167]},"n":["0p833_0p833_0p167_0p167"],"t":86,"s":[0],"e":[100]},{"i":{"x":[0.833],"y":[0.833]},"o":{"x":[0.167],"y":[0.167]},"n":["0p833_0p833_0p167_0p167"],"t":90,"s":[100],"e":[100]},{"i":{"x":[0.833],"y":[0.833]},"o":{"x":[0.167],"y":[0.167]},"n":["0p833_0p833_0p167_0p167"],"t":103,"s":[100],"e":[0]},{"t":108}],"ix":11},"r":{"a":0,"k":0,"ix":10},"p":{"a":0,"k":[66.5,88.25,0],"ix":2},"a":{"a":0,"k":[0,0,0],"ix":1},"s":{"a":1,"k":[{"i":{"x":[0.384,0.384,0.667],"y":[0.997,0.997,1]},"o":{"x":[0.106,0.106,0.333],"y":[-0.006,-0.006,0]},"n":["0p384_0p997_0p106_-0p006","0p384_0p997_0p106_-0p006","0p667_1_0p333_0"],"t":95,"s":[100,100,100],"e":[108,108,100]},{"t":108}],"ix":6}},"ao":0,"t":{"d":{"k":[{"s":{"sz":[150,38.5],"ps":[-75,-19.25],"s":20,"f":"FivoSansModern-Heavy","t":"action A","j":2,"tr":0,"lh":24,"ls":0,"fc":[1,1,1]},"t":0}]},"p":{},"m":{"g":1,"a":{"a":0,"k":[0,0],"ix":2}},"a":[]},"ip":0,"op":375,"st":0,"bm":0},{"ddd":0,"ind":3,"ty":4,"nm":"cursor pointer","sr":1,"ks":{"o":{"a":0,"k":100,"ix":11},"r":{"a":1,"k":[{"i":{"x":[0.412],"y":[1.043]},"o":{"x":[0.236],"y":[0.01]},"n":["0p412_1p043_0p236_0p01"],"t":10,"s":[0],"e":[-9]},{"i":{"x":[0.412],"y":[0.805]},"o":{"x":[0.333],"y":[0]},"n":["0p412_0p805_0p333_0"],"t":30,"s":[-9],"e":[-9]},{"i":{"x":[0.145],"y":[1.01]},"o":{"x":[0.447],"y":[0.017]},"n":["0p145_1p01_0p447_0p017"],"t":40,"s":[-9],"e":[12]},{"i":{"x":[0.145],"y":[1.166]},"o":{"x":[0.333],"y":[0]},"n":["0p145_1p166_0p333_0"],"t":63,"s":[12],"e":[12]},{"i":{"x":[0.667],"y":[1]},"o":{"x":[0.18],"y":[-0.005]},"n":["0p667_1_0p18_-0p005"],"t":81,"s":[12],"e":[-9]},{"i":{"x":[0.206],"y":[0.996]},"o":{"x":[0.103],"y":[0.099]},"n":["0p206_0p996_0p103_0p099"],"t":95,"s":[-9],"e":[-19]},{"i":{"x":[0.456],"y":[0.99]},"o":{"x":[0.167],"y":[0]},"n":["0p456_0p99_0p167_0"],"t":105,"s":[-19],"e":[0]},{"t":118}],"ix":10},"p":{"a":0,"k":[194.129,211.699,0],"ix":2},"a":{"a":0,"k":[24.375,56,0],"ix":1},"s":{"a":0,"k":[100,100,100],"ix":6}},"ao":0,"shapes":[{"ty":"gr","it":[{"ind":0,"ty":"sh","ix":1,"ks":{"a":0,"k":{"i":[[0,0],[0,0],[2.111,0],[0,-2.11],[0,0]],"o":[[0,0],[-0.001,-2.111],[-2.111,0],[0,0],[0,0]],"v":[[3.839,9.535],[3.839,-13.676],[0,-17.516],[-3.839,-13.678],[-3.839,17.516]],"c":false},"ix":2},"nm":"Tracé 1","mn":"ADBE Vector Shape - Group","hd":false},{"ty":"st","c":{"a":0,"k":[1,1,1,1],"ix":3},"o":{"a":0,"k":100,"ix":4},"w":{"a":0,"k":1,"ix":5},"lc":1,"lj":1,"ml":10,"ml2":{"a":0,"k":10,"ix":8},"nm":"Contour 1","mn":"ADBE Vector Graphic - Stroke","hd":false},{"ty":"fl","c":{"a":0,"k":[1,0.623529411765,0,1],"ix":4},"o":{"a":0,"k":100,"ix":5},"r":1,"nm":"Fond 1","mn":"ADBE Vector Graphic - Fill","hd":false},{"ty":"tr","p":{"a":0,"k":[16.57,17.516],"ix":2},"a":{"a":0,"k":[0,0],"ix":1},"s":{"a":0,"k":[100,100],"ix":3},"r":{"a":0,"k":0,"ix":6},"o":{"a":0,"k":100,"ix":7},"sk":{"a":0,"k":0,"ix":4},"sa":{"a":0,"k":0,"ix":5},"nm":"Transformer "}],"nm":"Groupe 1","np":3,"cix":2,"ix":1,"mn":"ADBE Vector Group","hd":false},{"ty":"gr","it":[{"ind":0,"ty":"sh","ix":1,"ks":{"a":0,"k":{"i":[[0,0],[0,0],[-2.112,0],[0,-2.111],[0,0]],"o":[[0,0],[0,-2.112],[2.111,0],[0,0],[0,0]],"v":[[-3.839,5.374],[-3.839,-3.07],[0.001,-6.91],[3.839,-3.07],[3.839,6.91]],"c":false},"ix":2},"nm":"Tracé 1","mn":"ADBE Vector Shape - Group","hd":false},{"ty":"st","c":{"a":0,"k":[1,1,1,1],"ix":3},"o":{"a":0,"k":100,"ix":4},"w":{"a":0,"k":1,"ix":5},"lc":1,"lj":1,"ml":10,"ml2":{"a":0,"k":10,"ix":8},"nm":"Contour 1","mn":"ADBE Vector Graphic - Stroke","hd":false},{"ty":"fl","c":{"a":0,"k":[1,0.623529411765,0,1],"ix":4},"o":{"a":0,"k":100,"ix":5},"r":1,"nm":"Fond 1","mn":"ADBE Vector Graphic - Fill","hd":false},{"ty":"tr","p":{"a":0,"k":[23.068,21.219],"ix":2},"a":{"a":0,"k":[0,0],"ix":1},"s":{"a":0,"k":[100,100],"ix":3},"r":{"a":0,"k":0,"ix":6},"o":{"a":0,"k":100,"ix":7},"sk":{"a":0,"k":0,"ix":4},"sa":{"a":0,"k":0,"ix":5},"nm":"Transformer "}],"nm":"Groupe 2","np":3,"cix":2,"ix":2,"mn":"ADBE Vector Group","hd":false},{"ty":"gr","it":[{"ind":0,"ty":"sh","ix":1,"ks":{"a":0,"k":{"i":[[0,0],[0,0],[-2.11,-0.001],[0.001,-2.112],[0,0]],"o":[[0,0],[0,-2.112],[2.112,0],[0,0],[0,0]],"v":[[-3.839,4.223],[-3.839,-2.686],[-0.001,-6.525],[3.838,-2.686],[3.838,6.526]],"c":false},"ix":2},"nm":"Tracé 1","mn":"ADBE Vector Shape - Group","hd":false},{"ty":"st","c":{"a":0,"k":[1,1,1,1],"ix":3},"o":{"a":0,"k":100,"ix":4},"w":{"a":0,"k":1,"ix":5},"lc":1,"lj":1,"ml":10,"ml2":{"a":0,"k":10,"ix":8},"nm":"Contour 1","mn":"ADBE Vector Graphic - Stroke","hd":false},{"ty":"fl","c":{"a":0,"k":[1,0.623529411765,0,1],"ix":4},"o":{"a":0,"k":100,"ix":5},"r":1,"nm":"Fond 1","mn":"ADBE Vector Graphic - Fill","hd":false},{"ty":"tr","p":{"a":0,"k":[29.566,22.828],"ix":2},"a":{"a":0,"k":[0,0],"ix":1},"s":{"a":0,"k":[100,100],"ix":3},"r":{"a":0,"k":0,"ix":6},"o":{"a":0,"k":100,"ix":7},"sk":{"a":0,"k":0,"ix":4},"sa":{"a":0,"k":0,"ix":5},"nm":"Transformer "}],"nm":"Groupe 3","np":3,"cix":2,"ix":3,"mn":"ADBE Vector Group","hd":false},{"ty":"gr","it":[{"ind":0,"ty":"sh","ix":1,"ks":{"a":0,"k":{"i":[[0,0],[0,0],[-2.111,0],[0,-2.11],[0,0]],"o":[[0,0],[0,-2.111],[2.112,0],[0,0],[0,0]],"v":[[-3.839,2.27],[-3.839,-2.688],[-0.001,-6.525],[3.839,-2.688],[3.839,6.525]],"c":false},"ix":2},"nm":"Tracé 1","mn":"ADBE Vector Shape - Group","hd":false},{"ty":"st","c":{"a":0,"k":[1,1,1,1],"ix":3},"o":{"a":0,"k":100,"ix":4},"w":{"a":0,"k":1,"ix":5},"lc":1,"lj":1,"ml":10,"ml2":{"a":0,"k":10,"ix":8},"nm":"Contour 1","mn":"ADBE Vector Graphic - Stroke","hd":false},{"ty":"fl","c":{"a":0,"k":[1,0.623529411765,0,1],"ix":4},"o":{"a":0,"k":100,"ix":5},"r":1,"nm":"Fond 1","mn":"ADBE Vector Graphic - Fill","hd":false},{"ty":"tr","p":{"a":0,"k":[36.063,25.635],"ix":2},"a":{"a":0,"k":[0,0],"ix":1},"s":{"a":0,"k":[100,100],"ix":3},"r":{"a":0,"k":0,"ix":6},"o":{"a":0,"k":100,"ix":7},"sk":{"a":0,"k":0,"ix":4},"sa":{"a":0,"k":0,"ix":5},"nm":"Transformer "}],"nm":"Groupe 4","np":3,"cix":2,"ix":4,"mn":"ADBE Vector Group","hd":false},{"ty":"gr","it":[{"ind":0,"ty":"sh","ix":1,"ks":{"a":0,"k":{"i":[[0,0],[0,0],[2.104,-0.982],[-1.071,-2.296],[0,0],[-3.314,0],[0,0],[0,4.418],[0,0],[1.486,-0.12]],"o":[[0,0],[-1.07,-2.296],[-2.105,0.981],[0,0],[1.185,3.096],[0,0],[4.419,0],[0,0],[0,0],[0,0]],"v":[[-6.915,-3.575],[-11.529,-15.707],[-17.303,-18.097],[-19.182,-12.138],[-9.199,13.939],[-1.729,19.079],[12.254,19.079],[20.253,11.079],[20.253,-13.51],[-6.915,-13.51]],"c":true},"ix":2},"nm":"Tracé 1","mn":"ADBE Vector Shape - Group","hd":false},{"ty":"st","c":{"a":0,"k":[1,1,1,1],"ix":3},"o":{"a":0,"k":100,"ix":4},"w":{"a":0,"k":1,"ix":5},"lc":1,"lj":3,"nm":"Contour 1","mn":"ADBE Vector Graphic - Stroke","hd":false},{"ty":"tr","p":{"a":0,"k":[19.647,36.58],"ix":2},"a":{"a":0,"k":[0,0],"ix":1},"s":{"a":0,"k":[100,100],"ix":3},"r":{"a":0,"k":0,"ix":6},"o":{"a":0,"k":100,"ix":7},"sk":{"a":0,"k":0,"ix":4},"sa":{"a":0,"k":0,"ix":5},"nm":"Transformer "}],"nm":"Groupe 5","np":2,"cix":2,"ix":5,"mn":"ADBE Vector Group","hd":false},{"ty":"gr","it":[{"ind":0,"ty":"sh","ix":1,"ks":{"a":0,"k":{"i":[[0,0],[0,0],[2.104,-0.982],[-1.071,-2.296],[0,0],[-3.314,0],[0,0],[0,4.418],[0,0],[1.486,-0.12]],"o":[[0,0],[-1.07,-2.296],[-2.105,0.981],[0,0],[1.185,3.096],[0,0],[4.419,0],[0,0],[0,0],[0,0]],"v":[[-7.219,-3.575],[-11.833,-15.707],[-17.606,-18.097],[-19.486,-12.138],[-9.503,13.939],[-2.032,19.079],[11.95,19.079],[19.95,11.079],[19.95,-13.51],[-7.219,-13.51]],"c":true},"ix":2},"nm":"Tracé 1","mn":"ADBE Vector Shape - Group","hd":false},{"ty":"fl","c":{"a":0,"k":[1,0.623529411765,0,1],"ix":4},"o":{"a":0,"k":100,"ix":5},"r":1,"nm":"Fond 1","mn":"ADBE Vector Graphic - Fill","hd":false},{"ty":"tr","p":{"a":0,"k":[19.95,36.58],"ix":2},"a":{"a":0,"k":[0,0],"ix":1},"s":{"a":0,"k":[100,100],"ix":3},"r":{"a":0,"k":0,"ix":6},"o":{"a":0,"k":100,"ix":7},"sk":{"a":0,"k":0,"ix":4},"sa":{"a":0,"k":0,"ix":5},"nm":"Transformer "}],"nm":"Groupe 6","np":4,"cix":2,"ix":6,"mn":"ADBE Vector Group","hd":false}],"ip":0,"op":187,"st":0,"bm":0},{"ddd":0,"ind":6,"ty":4,"nm":"carte 1","parent":3,"sr":1,"ks":{"o":{"a":1,"k":[{"i":{"x":[0.833],"y":[0.833]},"o":{"x":[0.167],"y":[0.167]},"n":["0p833_0p833_0p167_0p167"],"t":97,"s":[100],"e":[0]},{"t":105}],"ix":11},"r":{"a":1,"k":[{"i":{"x":[0.206],"y":[0.998]},"o":{"x":[0.103],"y":[0.037]},"n":["0p206_0p998_0p103_0p037"],"t":95,"s":[0],"e":[-27]},{"t":105}],"ix":10},"p":{"s":true,"x":{"a":1,"k":[{"i":{"x":[0.206],"y":[0.999]},"o":{"x":[0.103],"y":[0.016]},"n":["0p206_0p999_0p103_0p016"],"t":95,"s":[17.746],"e":[-43.713]},{"t":105}],"ix":3},"y":{"a":1,"k":[{"i":{"x":[0.206],"y":[0.998]},"o":{"x":[0.103],"y":[0.047]},"n":["0p206_0p998_0p103_0p047"],"t":95,"s":[27.493],"e":[6.331]},{"t":105}],"ix":4}},"a":{"a":0,"k":[0,56.692,0],"ix":1},"s":{"a":0,"k":[100,100,100],"ix":6}},"ao":0,"shapes":[{"ty":"gr","it":[{"ty":"rc","d":1,"s":{"a":0,"k":[75,115.385],"ix":2},"p":{"a":0,"k":[0,0],"ix":3},"r":{"a":0,"k":10,"ix":4},"nm":"Tracé rectangulaire 1","mn":"ADBE Vector Shape - Rect","hd":false},{"ty":"st","c":{"a":0,"k":[0,0,0,1],"ix":3},"o":{"a":0,"k":100,"ix":4},"w":{"a":0,"k":1,"ix":5},"lc":1,"lj":1,"ml":4,"ml2":{"a":0,"k":4,"ix":8},"nm":"Contour 1","mn":"ADBE Vector Graphic - Stroke","hd":true},{"ty":"fl","c":{"a":0,"k":[1,1,1,1],"ix":4},"o":{"a":0,"k":100,"ix":5},"r":1,"nm":"Fond 1","mn":"ADBE Vector Graphic - Fill","hd":false},{"ty":"tr","p":{"a":0,"k":[0,0],"ix":2},"a":{"a":0,"k":[0,0],"ix":1},"s":{"a":0,"k":[100,100],"ix":3},"r":{"a":0,"k":0,"ix":6},"o":{"a":0,"k":100,"ix":7},"sk":{"a":0,"k":0,"ix":4},"sa":{"a":0,"k":0,"ix":5},"nm":"Transformer "}],"nm":"Rectangle 1","np":3,"cix":2,"ix":1,"mn":"ADBE Vector Group","hd":false}],"ip":0,"op":174,"st":0,"bm":0},{"ddd":0,"ind":7,"ty":4,"nm":"carte 2","sr":1,"ks":{"o":{"a":1,"k":[{"i":{"x":[0.833],"y":[0.833]},"o":{"x":[0.167],"y":[0.167]},"n":["0p833_0p833_0p167_0p167"],"t":0,"s":[50],"e":[50]},{"i":{"x":[0.833],"y":[0.833]},"o":{"x":[0.167],"y":[0.167]},"n":["0p833_0p833_0p167_0p167"],"t":97,"s":[50],"e":[100]},{"t":102}],"ix":11},"r":{"a":1,"k":[{"i":{"x":[0.833],"y":[0.833]},"o":{"x":[0.167],"y":[0.167]},"n":["0p833_0p833_0p167_0p167"],"t":0,"s":[8],"e":[5]},{"i":{"x":[0.833],"y":[0.833]},"o":{"x":[0.167],"y":[0.167]},"n":["0p833_0p833_0p167_0p167"],"t":97,"s":[5],"e":[0]},{"t":102}],"ix":10},"p":{"a":1,"k":[{"i":{"x":0.833,"y":0.833},"o":{"x":0.167,"y":0.167},"n":"0p833_0p833_0p167_0p167","t":97,"s":[187.5,125.5,0],"e":[187.5,126.5,0],"to":[0,0.16666667163372,0],"ti":[0,-0.16666667163372,0]},{"t":102}],"ix":2},"a":{"a":0,"k":[0,0,0],"ix":1},"s":{"a":0,"k":[100,100,100],"ix":6}},"ao":0,"shapes":[{"ty":"gr","it":[{"ty":"rc","d":1,"s":{"a":0,"k":[75,115.385],"ix":2},"p":{"a":0,"k":[0,0],"ix":3},"r":{"a":0,"k":10,"ix":4},"nm":"Tracé rectangulaire 1","mn":"ADBE Vector Shape - Rect","hd":false},{"ty":"st","c":{"a":0,"k":[0,0,0,1],"ix":3},"o":{"a":1,"k":[{"i":{"x":[0.833],"y":[0.833]},"o":{"x":[0.167],"y":[0.167]},"n":["0p833_0p833_0p167_0p167"],"t":0,"s":[0],"e":[0]},{"i":{"x":[0.833],"y":[0.833]},"o":{"x":[0.167],"y":[0.167]},"n":["0p833_0p833_0p167_0p167"],"t":100,"s":[0],"e":[100]},{"t":105}],"ix":4},"w":{"a":0,"k":1,"ix":5},"lc":1,"lj":1,"ml":4,"ml2":{"a":0,"k":4,"ix":8},"nm":"Contour 1","mn":"ADBE Vector Graphic - Stroke","hd":true},{"ty":"fl","c":{"a":0,"k":[1,1,1,1],"ix":4},"o":{"a":0,"k":100,"ix":5},"r":1,"nm":"Fond 1","mn":"ADBE Vector Graphic - Fill","hd":false},{"ty":"tr","p":{"a":0,"k":[0,0],"ix":2},"a":{"a":0,"k":[0,0],"ix":1},"s":{"a":0,"k":[100,100],"ix":3},"r":{"a":0,"k":0,"ix":6},"o":{"a":0,"k":100,"ix":7},"sk":{"a":0,"k":0,"ix":4},"sa":{"a":0,"k":0,"ix":5},"nm":"Transformer "}],"nm":"Rectangle 1","np":3,"cix":2,"ix":1,"mn":"ADBE Vector Group","hd":false}],"ip":0,"op":177,"st":0,"bm":0},{"ddd":0,"ind":8,"ty":4,"nm":"carte 3","sr":1,"ks":{"o":{"a":1,"k":[{"i":{"x":[0.833],"y":[0.833]},"o":{"x":[0.167],"y":[0.167]},"n":["0p833_0p833_0p167_0p167"],"t":97,"s":[0],"e":[50]},{"t":102}],"ix":11},"r":{"a":0,"k":8,"ix":10},"p":{"a":0,"k":[187.5,125.5,0],"ix":2},"a":{"a":0,"k":[0,0,0],"ix":1},"s":{"a":0,"k":[100,100,100],"ix":6}},"ao":0,"shapes":[{"ty":"gr","it":[{"ty":"rc","d":1,"s":{"a":0,"k":[75,115.385],"ix":2},"p":{"a":0,"k":[0,0],"ix":3},"r":{"a":0,"k":10,"ix":4},"nm":"Tracé rectangulaire 1","mn":"ADBE Vector Shape - Rect","hd":false},{"ty":"st","c":{"a":0,"k":[0,0,0,1],"ix":3},"o":{"a":0,"k":0,"ix":4},"w":{"a":0,"k":1,"ix":5},"lc":1,"lj":1,"ml":4,"ml2":{"a":0,"k":4,"ix":8},"nm":"Contour 1","mn":"ADBE Vector Graphic - Stroke","hd":true},{"ty":"fl","c":{"a":0,"k":[1,1,1,1],"ix":4},"o":{"a":0,"k":100,"ix":5},"r":1,"nm":"Fond 1","mn":"ADBE Vector Graphic - Fill","hd":false},{"ty":"tr","p":{"a":0,"k":[0,0],"ix":2},"a":{"a":0,"k":[0,0],"ix":1},"s":{"a":0,"k":[100,100],"ix":3},"r":{"a":0,"k":0,"ix":6},"o":{"a":0,"k":100,"ix":7},"sk":{"a":0,"k":0,"ix":4},"sa":{"a":0,"k":0,"ix":5},"nm":"Transformer "}],"nm":"Rectangle 1","np":3,"cix":2,"ix":1,"mn":"ADBE Vector Group","hd":false}],"ip":97,"op":274,"st":97,"bm":0}]}],"fonts":{"list":[{"origin":0,"fPath":"","fClass":"","fFamily":"Fivo Sans Modern","fWeight":"","fStyle":"Heavy","fName":"FivoSansModern-Heavy","ascent":69.9996948242188}]},"layers":[{"ddd":0,"ind":1,"ty":0,"nm":"TutorielEcran","refId":"comp_0","sr":1,"ks":{"o":{"a":0,"k":100,"ix":11},"r":{"a":0,"k":0,"ix":10},"p":{"a":0,"k":[132.5,234.5,0],"ix":2},"a":{"a":0,"k":[187.5,333.5,0],"ix":1},"s":{"a":0,"k":[80,80,100],"ix":6}},"ao":0,"w":375,"h":667,"ip":0,"op":375,"st":0,"bm":0}],"markers":[]}